Workbook
Name aporte_mensal: CONTROLE!$C$11
Name patrimonio: CONTROLE!$C$14
Name qd_meses: CONTROLE!$C$12
Name rend_carteira: CONTROLE!$D$7
Name salario: CONTROLE!$D$6
Name sug_invest: CONTROLE!$D$8

Sheet CONTROLE
B5: CONFIGURAÇÕES
B6: Salário | D6: 2000
B7: Rendimento carteira | D7: 0.006
B8: Sugestão de investimento | C8: 0.3 | D8: =D6*C8 -> 600
B10: INVESTIMENTOS MENSAIS
B11: Quanto investir por mês? | C11: 200
B12: Por quantos meses? | C12: 60
B13: Taxa de rendimento mensal? | C13: 0.01079
B14: Patrimônio acumulado | C14: =FV(C13,C12,-C11) -> 16755.383
B15: Dividendos Mensais | C15: =C14*C13 -> 180.79058
B17: CENÁRIOS
B18: Quanto em (anos): | C18: Patrimônio acumulado | D18: Dividendos
B19: 2 | C19: =FV($C$13,B19*12,-$C$11) -> 5445.5255 | D19: =C19*rend_carteira -> 32.673153
B20: 5 | C20: =FV($C$13,B20*12,-$C$11) -> 16755.383 | D20: =C20*rend_carteira -> 100.5323
B21: 10 | C21: =FV($C$13,B21*12,-$C$11) -> 48656.843 | D21: =C21*rend_carteira -> 291.94106
B22: 20 | C22: =FV($C$13,B22*12,-$C$11) -> 225039.68 | D22: =C22*rend_carteira -> 1350.2381
B23: 30 | C23: =FV($C$13,B23*12,-$C$11) -> 864433.93 | D23: =C23*rend_carteira -> 5186.6036
B24: outro (insira aqui) | C24: =FV($C$13,B24*12,-$C$11) -> #VALUE! | D24: =C24*rend_carteira -> #VALUE!
B26: PERFIL: | C26: Conservador
B27: Valor mensal a ser investido | C27: =aporte_mensal -> 200
B29: Tipo de FII | C29: % sugerido | D29: Valores
B30: PAPEL | C30: =VLOOKUP($C$26&"-"&B30,APOIO!A3:D21,4,FALSE) -> 0.3 | D30: =$C$27*C30 -> 60
B31: TIJOLO | C31: =VLOOKUP($C$26&"-"&B31,APOIO!A4:D22,4,FALSE) -> 0.5 | D31: =$C$27*C31 -> 100
B32: HÍBRIDOS | C32: =VLOOKUP($C$26&"-"&B32,APOIO!A5:D23,4,FALSE) -> 0.1 | D32: =$C$27*C32 -> 20
B33: FOFs | C33: =VLOOKUP($C$26&"-"&B33,APOIO!A6:D24,4,FALSE) -> 0.1 | D33: =$C$27*C33 -> 20
B34: DESENVOLVIMENTO | C34: =VLOOKUP($C$26&"-"&B34,APOIO!A7:D25,4,FALSE) -> 0 | D34: =$C$27*C34 -> 0
B35: HOTELARIAS | C35: =VLOOKUP($C$26&"-"&B35,APOIO!A8:D26,4,FALSE) -> 0 | D35: =$C$27*C35 -> 0
D36: =SUM(D30:D35) -> 200

Sheet APOIO
A3: CHAVE COMPOSTA | B3: PERFIL | C3: TIPO DE FII | D3: %
A4: =B4&"-"&C4 -> Conservador-PAPEL | B4: Conservador | C4: PAPEL | D4: 0.3
A5: =B5&"-"&C5 -> Conservador-TIJOLO | B5: Conservador | C5: TIJOLO | D5: 0.5
A6: =B6&"-"&C6 -> Conservador-HÍBRIDOS | B6: Conservador | C6: HÍBRIDOS | D6: 0.1
A7: =B7&"-"&C7 -> Conservador-FOFs | B7: Conservador | C7: FOFs | D7: 0.1
A8: =B8&"-"&C8 -> Conservador-DESENVOLVIMENTO | B8: Conservador | C8: DESENVOLVIMENTO | D8: 0
A9: =B9&"-"&C9 -> Conservador-HOTELARIAS | B9: Conservador | C9: HOTELARIAS | D9: 0
A10: =B10&"-"&C10 -> Moderado-PAPEL | B10: Moderado | C10: PAPEL | D10: 0.32
A11: =B11&"-"&C11 -> Moderado-TIJOLO | B11: Moderado | C11: TIJOLO | D11: 0.35
A12: =B12&"-"&C12 -> Moderado-HÍBRIDOS | B12: Moderado | C12: HÍBRIDOS | D12: 0.08
A13: =B13&"-"&C13 -> Moderado-FOFs | B13: Moderado | C13: FOFs | D13: 0.05
A14: =B14&"-"&C14 -> Moderado-DESENVOLVIMENTO | B14: Moderado | C14: DESENVOLVIMENTO | D14: 0.1
A15: =B15&"-"&C15 -> Moderado-HOTELARIAS | B15: Moderado | C15: HOTELARIAS | D15: 0.1
... A21: =B21&"-"&C21 -> Agressivo-HOTELARIAS | B21: Agressivo | C21: HOTELARIAS | D21: 0.1
